<NFe>
  <Prefeitura>Bauru</Prefeitura>
  <InscricaoPrestador>577280</InscricaoPrestador>
  <IEPrestador></IEPrestador>
  <CPFCNPJPrestador>
    <CNPJ>31002663000179</CNPJ>
  </CPFCNPJPrestador>
  <ChaveNFe>
    <NumeroNFe>1069</NumeroNFe>
    <SerieNFe>1</SerieNFe>
    <CodigoVerificacao>C91FEA8D23E78239246B2F041EC76CA6</CodigoVerificacao>
    <DataEmissaoNFe>2020-01-17</DataEmissaoNFe>
  </ChaveNFe>
  <RazaoSocialPrestador>F D M DOS SANTOS LOPES E AVELAR</RazaoSocialPrestador>
  <EnderecoPrestador>
    <Logradouro>RUA ALFREDO FONTAO</Logradouro>
    <NumeroEndereco>2-73</NumeroEndereco>
    <ComplementoEndereco></ComplementoEndereco>
    <Bairro>JD. PAULISTA</Bairro>
    <Cidade>BAURU</Cidade>
    <UF>SP</UF>
    <CEP>17017240</CEP>
  </EnderecoPrestador>
  <TelefonePrestador>1438781212</TelefonePrestador>
  <EmailPrestador>ilton@esolucao.net</EmailPrestador>
  <StatusNFe>Ativa</StatusNFe>
  <TributacaoNFe>Tributada no Prestador</TributacaoNFe>
  <OpcaoSimples>NÃO</OpcaoSimples>
  <ValorServicos>397,50</ValorServicos>
  <ValorBase>397,50</ValorBase>
  <CodigoServico>412</CodigoServico>
  <AliquotaServicos>2,00</AliquotaServicos>
  <ValorINSS>0,00</ValorINSS>
  <ValorIR>0,00</ValorIR>
  <ValorPIS>0,00</ValorPIS>
  <ValorCOFINS>0,00</ValorCOFINS>
  <ValorCSLL>0,00</ValorCSLL>
  <ValorISS>7,95</ValorISS>
  <ValorISSFora></ValorISSFora>
  <ISSRetido>NÃO</ISSRetido>
  <InscricaoTomador></InscricaoTomador>
  <CPFCNPJTomador>
    <CNPJ>06806798802</CNPJ>
  </CPFCNPJTomador>
  <IETomador></IETomador>
  <RazaoSocialTomador>MARTA MARIA CAPUANI PEREIRA GOMES</RazaoSocialTomador>
  <EnderecoTomador>
    <Logradouro>RUA ANTÔNIO GALVES</Logradouro>
    <NumeroEndereco>1-118</NumeroEndereco>
    <ComplementoEndereco></ComplementoEndereco>
    <Bairro>NÚCLEO HABITACIONAL VANUIRE</Bairro>
    <Cidade>BAURU</Cidade>
    <UF>SP</UF>
    <CEP>17022830</CEP>
  </EnderecoTomador>
  <LocalServico>
    <LocalServicoEstado></LocalServicoEstado>
    <LocalServicoCidade></LocalServicoCidade>
  </LocalServico>
  <TelefoneTomador></TelefoneTomador>
  <EmailTomador>martacapuani@hotmail.com</EmailTomador>
  <Discriminacao>SERVIÇOS ODONTOLÓGICOS</Discriminacao>
  <ServicoExportacao>NÃO</ServicoExportacao>
</NFe>