<?xml version="1.0" standalone="yes"?>
<DsExportarNotaFiscal xmlns="http://tempuri.org/DsExportarNotaFiscal.xsd">
  <TbNotasFiscais>
    <NumeroNF>2047</NumeroNF>
    <DtEmissao>2019-12-18T00:00:00-03:00</DtEmissao>
    <Assinatura>8410371575318/12/2019</Assinatura>
    <CNPJCPFTomador>650.122.325-34</CNPJCPFTomador>
    <Status>1</Status>
    <ValorTotal>730.0000</ValorTotal>
    <ValorDeducao>0.0000</ValorDeducao>
    <ImpDevido>25.55</ImpDevido>
    <ImpRetido>0</ImpRetido>
    <RetencaoIRRF>0.0000</RetencaoIRRF>
    <RetencaoPIS>0.0000</RetencaoPIS>
    <RetencaoCOFINS>0.0000</RetencaoCOFINS>
    <RetencaoCSLL>0.0000</RetencaoCSLL>
    <RetencaoINSS>0.0000</RetencaoINSS>
    <Observacoes>134,53</Observacoes>
    <BaseCalculo>730.0000</BaseCalculo>
    <NomeRazaoTomador>PAULO MARCELO PIRES BASTOS</NomeRazaoTomador>
    <MunicipioTomador>IRECÊ</MunicipioTomador>
  </TbNotasFiscais>
  <TbNotasFiscais>
    <NumeroNF>2048</NumeroNF>
    <DtEmissao>2019-12-19T00:00:00-03:00</DtEmissao>
    <Assinatura>8410371800719/12/2019</Assinatura>
    <CNPJCPFTomador>004.613.815-32</CNPJCPFTomador>
    <Status>1</Status>
    <ValorTotal>145.0000</ValorTotal>
    <ValorDeducao>0.0000</ValorDeducao>
    <ImpDevido>5.075</ImpDevido>
    <ImpRetido>0</ImpRetido>
    <RetencaoIRRF>0.0000</RetencaoIRRF>
    <RetencaoPIS>0.0000</RetencaoPIS>
    <RetencaoCOFINS>0.0000</RetencaoCOFINS>
    <RetencaoCSLL>0.0000</RetencaoCSLL>
    <RetencaoINSS>0.0000</RetencaoINSS>
    <Observacoes>26,72</Observacoes>
    <BaseCalculo>145.0000</BaseCalculo>
    <NomeRazaoTomador>MELKA BETINI COSTA OLIVEIRA MELO</NomeRazaoTomador>
    <MunicipioTomador>IRECÊ</MunicipioTomador>
  </TbNotasFiscais>
  <TbNotasFiscais>
    <NumeroNF>2049</NumeroNF>
    <DtEmissao>2019-12-20T00:00:00-03:00</DtEmissao>
    <Assinatura>8410372102220/12/2019</Assinatura>
    <CNPJCPFTomador>014.685.905-70</CNPJCPFTomador>
    <Status>1</Status>
    <ValorTotal>3030.0000</ValorTotal>
    <ValorDeducao>0.0000</ValorDeducao>
    <ImpDevido>106.05</ImpDevido>
    <ImpRetido>0</ImpRetido>
    <RetencaoIRRF>0.0000</RetencaoIRRF>
    <RetencaoPIS>0.0000</RetencaoPIS>
    <RetencaoCOFINS>0.0000</RetencaoCOFINS>
    <RetencaoCSLL>0.0000</RetencaoCSLL>
    <RetencaoINSS>0.0000</RetencaoINSS>
    <Observacoes>558,42</Observacoes>
    <BaseCalculo>3030.0000</BaseCalculo>
    <NomeRazaoTomador>RAFAEL PEREIRA LIMA </NomeRazaoTomador>
    <MunicipioTomador>IRECÊ</MunicipioTomador>
  </TbNotasFiscais>
  <TbNotasFiscais>
    <NumeroNF>2050</NumeroNF>
    <DtEmissao>2019-12-20T00:00:00-03:00</DtEmissao>
    <Assinatura>8410372153720/12/2019</Assinatura>
    <CNPJCPFTomador>014.685.905-70</CNPJCPFTomador>
    <Status>1</Status>
    <ValorTotal>700.0000</ValorTotal>
    <ValorDeducao>0.0000</ValorDeducao>
    <ImpDevido>24.5</ImpDevido>
    <ImpRetido>0</ImpRetido>
    <RetencaoIRRF>0.0000</RetencaoIRRF>
    <RetencaoPIS>0.0000</RetencaoPIS>
    <RetencaoCOFINS>0.0000</RetencaoCOFINS>
    <RetencaoCSLL>0.0000</RetencaoCSLL>
    <RetencaoINSS>0.0000</RetencaoINSS>
    <Observacoes>129,01</Observacoes>
    <BaseCalculo>700.0000</BaseCalculo>
    <NomeRazaoTomador>RAFAEL PEREIRA LIMA </NomeRazaoTomador>
    <MunicipioTomador>IRECÊ</MunicipioTomador>
  </TbNotasFiscais>
  <TbNotasFiscais>
    <NumeroNF>2051</NumeroNF>
    <DtEmissao>2019-12-20T00:00:00-03:00</DtEmissao>
    <Assinatura>8410372156620/12/2019</Assinatura>
    <CNPJCPFTomador>014.685.905-70</CNPJCPFTomador>
    <Status>1</Status>
    <ValorTotal>410.0000</ValorTotal>
    <ValorDeducao>0.0000</ValorDeducao>
    <ImpDevido>14.35</ImpDevido>
    <ImpRetido>0</ImpRetido>
    <RetencaoIRRF>0.0000</RetencaoIRRF>
    <RetencaoPIS>0.0000</RetencaoPIS>
    <RetencaoCOFINS>0.0000</RetencaoCOFINS>
    <RetencaoCSLL>0.0000</RetencaoCSLL>
    <RetencaoINSS>0.0000</RetencaoINSS>
    <Observacoes>75,56</Observacoes>
    <BaseCalculo>410.0000</BaseCalculo>
    <NomeRazaoTomador>RAFAEL PEREIRA LIMA </NomeRazaoTomador>
    <MunicipioTomador>IRECÊ</MunicipioTomador>
  </TbNotasFiscais>
  <TbNotasFiscais>
    <NumeroNF>2052</NumeroNF>
    <DtEmissao>2019-12-20T00:00:00-03:00</DtEmissao>
    <Assinatura>8410372315920/12/2019</Assinatura>
    <CNPJCPFTomador>704.498.055-49</CNPJCPFTomador>
    <Status>1</Status>
    <ValorTotal>270.0000</ValorTotal>
    <ValorDeducao>0.0000</ValorDeducao>
    <ImpDevido>9.45</ImpDevido>
    <ImpRetido>0</ImpRetido>
    <RetencaoIRRF>0.0000</RetencaoIRRF>
    <RetencaoPIS>0.0000</RetencaoPIS>
    <RetencaoCOFINS>0.0000</RetencaoCOFINS>
    <RetencaoCSLL>0.0000</RetencaoCSLL>
    <RetencaoINSS>0.0000</RetencaoINSS>
    <Observacoes>49,76</Observacoes>
    <BaseCalculo>270.0000</BaseCalculo>
    <NomeRazaoTomador>JOÃO MARCOS CAMBUÍ CHAGAS </NomeRazaoTomador>
    <MunicipioTomador>IRECÊ</MunicipioTomador>
  </TbNotasFiscais>
  <TbNotasFiscais>
    <NumeroNF>2053</NumeroNF>
    <DtEmissao>2019-12-24T00:00:00-03:00</DtEmissao>
    <Assinatura>8410372768124/12/2019</Assinatura>
    <CNPJCPFTomador>037.998.355-98</CNPJCPFTomador>
    <Status>2</Status>
    <ValorTotal>100.0000</ValorTotal>
    <ValorDeducao>0.0000</ValorDeducao>
    <ImpDevido>3.5</ImpDevido>
    <ImpRetido>0</ImpRetido>
    <RetencaoIRRF>0.0000</RetencaoIRRF>
    <RetencaoPIS>0.0000</RetencaoPIS>
    <RetencaoCOFINS>0.0000</RetencaoCOFINS>
    <RetencaoCSLL>0.0000</RetencaoCSLL>
    <RetencaoINSS>0.0000</RetencaoINSS>
    <Observacoes> 18,43</Observacoes>
    <BaseCalculo>100.0000</BaseCalculo>
    <NomeRazaoTomador>ARMANDO JAIME RAMOS DA SILVA CAMPOS </NomeRazaoTomador>
    <MunicipioTomador>IRECÊ</MunicipioTomador>
  </TbNotasFiscais>
  <TbNotasFiscais>
    <NumeroNF>2054</NumeroNF>
    <DtEmissao>2019-12-26T00:00:00-03:00</DtEmissao>
    <Assinatura>8410373033826/12/2019</Assinatura>
    <CNPJCPFTomador>037.998.355-98</CNPJCPFTomador>
    <Status>1</Status>
    <ValorTotal>100.0000</ValorTotal>
    <ValorDeducao>0.0000</ValorDeducao>
    <ImpDevido>3.5</ImpDevido>
    <ImpRetido>0</ImpRetido>
    <RetencaoIRRF>0.0000</RetencaoIRRF>
    <RetencaoPIS>0.0000</RetencaoPIS>
    <RetencaoCOFINS>0.0000</RetencaoCOFINS>
    <RetencaoCSLL>0.0000</RetencaoCSLL>
    <RetencaoINSS>0.0000</RetencaoINSS>
    <Observacoes> 18,43 EM SUBSTITUIÇÃO DA NF Nº 2053 EMITIDA EM: 24/12/2019 13:59:22</Observacoes>
    <BaseCalculo>100.0000</BaseCalculo>
    <NomeRazaoTomador>ARMANDO JAIME RAMOS DA SILVA CAMPOS </NomeRazaoTomador>
    <MunicipioTomador>IRECÊ</MunicipioTomador>
  </TbNotasFiscais>
  <TbNotasFiscais>
    <NumeroNF>2055</NumeroNF>
    <DtEmissao>2019-12-27T00:00:00-03:00</DtEmissao>
    <Assinatura>8410373278727/12/2019</Assinatura>
    <CNPJCPFTomador>008.877.395-71</CNPJCPFTomador>
    <Status>1</Status>
    <ValorTotal>370.0000</ValorTotal>
    <ValorDeducao>0.0000</ValorDeducao>
    <ImpDevido>12.95</ImpDevido>
    <ImpRetido>0</ImpRetido>
    <RetencaoIRRF>0.0000</RetencaoIRRF>
    <RetencaoPIS>0.0000</RetencaoPIS>
    <RetencaoCOFINS>0.0000</RetencaoCOFINS>
    <RetencaoCSLL>0.0000</RetencaoCSLL>
    <RetencaoINSS>0.0000</RetencaoINSS>
    <Observacoes>62,66</Observacoes>
    <BaseCalculo>370.0000</BaseCalculo>
    <NomeRazaoTomador>CRISTIANE KUHN DE OLIVEIRA</NomeRazaoTomador>
    <MunicipioTomador>JUSSARA</MunicipioTomador>
  </TbNotasFiscais>
  <TbNotasFiscais>
    <NumeroNF>2056</NumeroNF>
    <DtEmissao>2019-12-27T00:00:00-03:00</DtEmissao>
    <Assinatura>8410373281827/12/2019</Assinatura>
    <CNPJCPFTomador>030.696.908-40</CNPJCPFTomador>
    <Status>1</Status>
    <ValorTotal>1885.0000</ValorTotal>
    <ValorDeducao>0.0000</ValorDeducao>
    <ImpDevido>65.975</ImpDevido>
    <ImpRetido>0</ImpRetido>
    <RetencaoIRRF>0.0000</RetencaoIRRF>
    <RetencaoPIS>0.0000</RetencaoPIS>
    <RetencaoCOFINS>0.0000</RetencaoCOFINS>
    <RetencaoCSLL>0.0000</RetencaoCSLL>
    <RetencaoINSS>0.0000</RetencaoINSS>
    <Observacoes>347,40</Observacoes>
    <BaseCalculo>1885.0000</BaseCalculo>
    <NomeRazaoTomador>LUZIA ALVES SERRA </NomeRazaoTomador>
    <MunicipioTomador>JUSSARA</MunicipioTomador>
  </TbNotasFiscais>
</DsExportarNotaFiscal>